{
  "schema_version": 1,
  "generated_at": "2026-05-16T22:18:38Z",
  "commit_sha": "3238ec9b43407d283d0014433913bb4785f28dfc",
  "commit_short": "3238ec9b43",
  "repo": "zackseyun/peoples-open-bible",
  "totals": {
    "books_drafted": 66,
    "books_total": 66,
    "chapters_drafted": 1188,
    "chapters_total": 1189,
    "verses_drafted": 31109,
    "verses_total": 31102,
    "nt": {
      "books_drafted": 27,
      "books_total": 27,
      "chapters_drafted": 260,
      "chapters_total": 260,
      "verses_drafted": 7957,
      "verses_total": 7957
    },
    "ot": {
      "books_drafted": 39,
      "books_total": 39,
      "chapters_drafted": 928,
      "chapters_total": 929,
      "verses_drafted": 23152,
      "verses_total": 23145
    },
    "deuterocanon": {
      "books_drafted": 18,
      "books_total": 18,
      "chapters_drafted": 200,
      "chapters_total": 200,
      "verses_drafted": 6075,
      "verses_total": 5928
    },
    "extra_canonical": {
      "books_drafted": 11,
      "books_total": 11,
      "chapters_drafted": 801,
      "chapters_total": 801,
      "verses_drafted": 5370,
      "verses_total": 5196
    }
  },
  "books": [
    {
      "book": "Matthew",
      "code": "MAT",
      "testament": "nt",
      "slug": "matthew",
      "chapters_total": 28,
      "verses_total": 1071,
      "chapters_drafted": 28,
      "verses_drafted": 1071
    },
    {
      "book": "Mark",
      "code": "MRK",
      "testament": "nt",
      "slug": "mark",
      "chapters_total": 16,
      "verses_total": 678,
      "chapters_drafted": 16,
      "verses_drafted": 678
    },
    {
      "book": "Luke",
      "code": "LUK",
      "testament": "nt",
      "slug": "luke",
      "chapters_total": 24,
      "verses_total": 1151,
      "chapters_drafted": 24,
      "verses_drafted": 1151
    },
    {
      "book": "John",
      "code": "JHN",
      "testament": "nt",
      "slug": "john",
      "chapters_total": 21,
      "verses_total": 879,
      "chapters_drafted": 21,
      "verses_drafted": 879
    },
    {
      "book": "Acts",
      "code": "ACT",
      "testament": "nt",
      "slug": "acts",
      "chapters_total": 28,
      "verses_total": 1006,
      "chapters_drafted": 28,
      "verses_drafted": 1006
    },
    {
      "book": "Romans",
      "code": "ROM",
      "testament": "nt",
      "slug": "romans",
      "chapters_total": 16,
      "verses_total": 433,
      "chapters_drafted": 16,
      "verses_drafted": 433
    },
    {
      "book": "1 Corinthians",
      "code": "1CO",
      "testament": "nt",
      "slug": "1_corinthians",
      "chapters_total": 16,
      "verses_total": 437,
      "chapters_drafted": 16,
      "verses_drafted": 437
    },
    {
      "book": "2 Corinthians",
      "code": "2CO",
      "testament": "nt",
      "slug": "2_corinthians",
      "chapters_total": 13,
      "verses_total": 256,
      "chapters_drafted": 13,
      "verses_drafted": 256
    },
    {
      "book": "Galatians",
      "code": "GAL",
      "testament": "nt",
      "slug": "galatians",
      "chapters_total": 6,
      "verses_total": 149,
      "chapters_drafted": 6,
      "verses_drafted": 149
    },
    {
      "book": "Ephesians",
      "code": "EPH",
      "testament": "nt",
      "slug": "ephesians",
      "chapters_total": 6,
      "verses_total": 155,
      "chapters_drafted": 6,
      "verses_drafted": 155
    },
    {
      "book": "Philippians",
      "code": "PHP",
      "testament": "nt",
      "slug": "philippians",
      "chapters_total": 4,
      "verses_total": 104,
      "chapters_drafted": 4,
      "verses_drafted": 104
    },
    {
      "book": "Colossians",
      "code": "COL",
      "testament": "nt",
      "slug": "colossians",
      "chapters_total": 4,
      "verses_total": 95,
      "chapters_drafted": 4,
      "verses_drafted": 95
    },
    {
      "book": "1 Thessalonians",
      "code": "1TH",
      "testament": "nt",
      "slug": "1_thessalonians",
      "chapters_total": 5,
      "verses_total": 89,
      "chapters_drafted": 5,
      "verses_drafted": 89
    },
    {
      "book": "2 Thessalonians",
      "code": "2TH",
      "testament": "nt",
      "slug": "2_thessalonians",
      "chapters_total": 3,
      "verses_total": 47,
      "chapters_drafted": 3,
      "verses_drafted": 47
    },
    {
      "book": "1 Timothy",
      "code": "1TI",
      "testament": "nt",
      "slug": "1_timothy",
      "chapters_total": 6,
      "verses_total": 113,
      "chapters_drafted": 6,
      "verses_drafted": 113
    },
    {
      "book": "2 Timothy",
      "code": "2TI",
      "testament": "nt",
      "slug": "2_timothy",
      "chapters_total": 4,
      "verses_total": 83,
      "chapters_drafted": 4,
      "verses_drafted": 83
    },
    {
      "book": "Titus",
      "code": "TIT",
      "testament": "nt",
      "slug": "titus",
      "chapters_total": 3,
      "verses_total": 46,
      "chapters_drafted": 3,
      "verses_drafted": 46
    },
    {
      "book": "Philemon",
      "code": "PHM",
      "testament": "nt",
      "slug": "philemon",
      "chapters_total": 1,
      "verses_total": 25,
      "chapters_drafted": 1,
      "verses_drafted": 25
    },
    {
      "book": "Hebrews",
      "code": "HEB",
      "testament": "nt",
      "slug": "hebrews",
      "chapters_total": 13,
      "verses_total": 303,
      "chapters_drafted": 13,
      "verses_drafted": 303
    },
    {
      "book": "James",
      "code": "JAS",
      "testament": "nt",
      "slug": "james",
      "chapters_total": 5,
      "verses_total": 108,
      "chapters_drafted": 5,
      "verses_drafted": 108
    },
    {
      "book": "1 Peter",
      "code": "1PE",
      "testament": "nt",
      "slug": "1_peter",
      "chapters_total": 5,
      "verses_total": 105,
      "chapters_drafted": 5,
      "verses_drafted": 105
    },
    {
      "book": "2 Peter",
      "code": "2PE",
      "testament": "nt",
      "slug": "2_peter",
      "chapters_total": 3,
      "verses_total": 61,
      "chapters_drafted": 3,
      "verses_drafted": 61
    },
    {
      "book": "1 John",
      "code": "1JN",
      "testament": "nt",
      "slug": "1_john",
      "chapters_total": 5,
      "verses_total": 105,
      "chapters_drafted": 5,
      "verses_drafted": 105
    },
    {
      "book": "2 John",
      "code": "2JN",
      "testament": "nt",
      "slug": "2_john",
      "chapters_total": 1,
      "verses_total": 13,
      "chapters_drafted": 1,
      "verses_drafted": 13
    },
    {
      "book": "3 John",
      "code": "3JN",
      "testament": "nt",
      "slug": "3_john",
      "chapters_total": 1,
      "verses_total": 15,
      "chapters_drafted": 1,
      "verses_drafted": 15
    },
    {
      "book": "Jude",
      "code": "JUD",
      "testament": "nt",
      "slug": "jude",
      "chapters_total": 1,
      "verses_total": 25,
      "chapters_drafted": 1,
      "verses_drafted": 25
    },
    {
      "book": "Revelation",
      "code": "REV",
      "testament": "nt",
      "slug": "revelation",
      "chapters_total": 22,
      "verses_total": 405,
      "chapters_drafted": 22,
      "verses_drafted": 405
    },
    {
      "book": "Genesis",
      "code": "GEN",
      "testament": "ot",
      "slug": "genesis",
      "chapters_total": 50,
      "verses_total": 1533,
      "chapters_drafted": 50,
      "verses_drafted": 1533
    },
    {
      "book": "Exodus",
      "code": "EXO",
      "testament": "ot",
      "slug": "exodus",
      "chapters_total": 40,
      "verses_total": 1213,
      "chapters_drafted": 40,
      "verses_drafted": 1213
    },
    {
      "book": "Leviticus",
      "code": "LEV",
      "testament": "ot",
      "slug": "leviticus",
      "chapters_total": 27,
      "verses_total": 859,
      "chapters_drafted": 27,
      "verses_drafted": 859
    },
    {
      "book": "Numbers",
      "code": "NUM",
      "testament": "ot",
      "slug": "numbers",
      "chapters_total": 36,
      "verses_total": 1288,
      "chapters_drafted": 36,
      "verses_drafted": 1289
    },
    {
      "book": "Deuteronomy",
      "code": "DEU",
      "testament": "ot",
      "slug": "deuteronomy",
      "chapters_total": 34,
      "verses_total": 959,
      "chapters_drafted": 34,
      "verses_drafted": 959
    },
    {
      "book": "Joshua",
      "code": "JOS",
      "testament": "ot",
      "slug": "joshua",
      "chapters_total": 24,
      "verses_total": 658,
      "chapters_drafted": 24,
      "verses_drafted": 658
    },
    {
      "book": "Judges",
      "code": "JDG",
      "testament": "ot",
      "slug": "judges",
      "chapters_total": 21,
      "verses_total": 618,
      "chapters_drafted": 21,
      "verses_drafted": 618
    },
    {
      "book": "Ruth",
      "code": "RUT",
      "testament": "ot",
      "slug": "ruth",
      "chapters_total": 4,
      "verses_total": 85,
      "chapters_drafted": 4,
      "verses_drafted": 85
    },
    {
      "book": "1 Samuel",
      "code": "1SA",
      "testament": "ot",
      "slug": "1_samuel",
      "chapters_total": 31,
      "verses_total": 810,
      "chapters_drafted": 31,
      "verses_drafted": 811
    },
    {
      "book": "2 Samuel",
      "code": "2SA",
      "testament": "ot",
      "slug": "2_samuel",
      "chapters_total": 24,
      "verses_total": 695,
      "chapters_drafted": 24,
      "verses_drafted": 695
    },
    {
      "book": "1 Kings",
      "code": "1KI",
      "testament": "ot",
      "slug": "1_kings",
      "chapters_total": 22,
      "verses_total": 816,
      "chapters_drafted": 22,
      "verses_drafted": 817
    },
    {
      "book": "2 Kings",
      "code": "2KI",
      "testament": "ot",
      "slug": "2_kings",
      "chapters_total": 25,
      "verses_total": 719,
      "chapters_drafted": 25,
      "verses_drafted": 719
    },
    {
      "book": "1 Chronicles",
      "code": "1CH",
      "testament": "ot",
      "slug": "1_chronicles",
      "chapters_total": 29,
      "verses_total": 942,
      "chapters_drafted": 29,
      "verses_drafted": 943
    },
    {
      "book": "2 Chronicles",
      "code": "2CH",
      "testament": "ot",
      "slug": "2_chronicles",
      "chapters_total": 36,
      "verses_total": 822,
      "chapters_drafted": 36,
      "verses_drafted": 822
    },
    {
      "book": "Ezra",
      "code": "EZR",
      "testament": "ot",
      "slug": "ezra",
      "chapters_total": 10,
      "verses_total": 280,
      "chapters_drafted": 10,
      "verses_drafted": 280
    },
    {
      "book": "Nehemiah",
      "code": "NEH",
      "testament": "ot",
      "slug": "nehemiah",
      "chapters_total": 13,
      "verses_total": 406,
      "chapters_drafted": 13,
      "verses_drafted": 405
    },
    {
      "book": "Esther",
      "code": "EST",
      "testament": "ot",
      "slug": "esther",
      "chapters_total": 10,
      "verses_total": 167,
      "chapters_drafted": 10,
      "verses_drafted": 167
    },
    {
      "book": "Job",
      "code": "JOB",
      "testament": "ot",
      "slug": "job",
      "chapters_total": 42,
      "verses_total": 1070,
      "chapters_drafted": 42,
      "verses_drafted": 1070
    },
    {
      "book": "Psalms",
      "code": "PSA",
      "testament": "ot",
      "slug": "psalms",
      "chapters_total": 150,
      "verses_total": 2461,
      "chapters_drafted": 149,
      "verses_drafted": 2466
    },
    {
      "book": "Proverbs",
      "code": "PRO",
      "testament": "ot",
      "slug": "proverbs",
      "chapters_total": 31,
      "verses_total": 915,
      "chapters_drafted": 31,
      "verses_drafted": 915
    },
    {
      "book": "Ecclesiastes",
      "code": "ECC",
      "testament": "ot",
      "slug": "ecclesiastes",
      "chapters_total": 12,
      "verses_total": 222,
      "chapters_drafted": 12,
      "verses_drafted": 222
    },
    {
      "book": "Song of Solomon",
      "code": "SNG",
      "testament": "ot",
      "slug": "song_of_songs",
      "chapters_total": 8,
      "verses_total": 117,
      "chapters_drafted": 8,
      "verses_drafted": 117
    },
    {
      "book": "Isaiah",
      "code": "ISA",
      "testament": "ot",
      "slug": "isaiah",
      "chapters_total": 66,
      "verses_total": 1292,
      "chapters_drafted": 66,
      "verses_drafted": 1291
    },
    {
      "book": "Jeremiah",
      "code": "JER",
      "testament": "ot",
      "slug": "jeremiah",
      "chapters_total": 52,
      "verses_total": 1364,
      "chapters_drafted": 52,
      "verses_drafted": 1364
    },
    {
      "book": "Lamentations",
      "code": "LAM",
      "testament": "ot",
      "slug": "lamentations",
      "chapters_total": 5,
      "verses_total": 154,
      "chapters_drafted": 5,
      "verses_drafted": 154
    },
    {
      "book": "Ezekiel",
      "code": "EZK",
      "testament": "ot",
      "slug": "ezekiel",
      "chapters_total": 48,
      "verses_total": 1273,
      "chapters_drafted": 48,
      "verses_drafted": 1273
    },
    {
      "book": "Daniel",
      "code": "DAN",
      "testament": "ot",
      "slug": "daniel",
      "chapters_total": 12,
      "verses_total": 357,
      "chapters_drafted": 12,
      "verses_drafted": 357
    },
    {
      "book": "Hosea",
      "code": "HOS",
      "testament": "ot",
      "slug": "hosea",
      "chapters_total": 14,
      "verses_total": 197,
      "chapters_drafted": 14,
      "verses_drafted": 197
    },
    {
      "book": "Joel",
      "code": "JOL",
      "testament": "ot",
      "slug": "joel",
      "chapters_total": 3,
      "verses_total": 73,
      "chapters_drafted": 4,
      "verses_drafted": 73
    },
    {
      "book": "Amos",
      "code": "AMO",
      "testament": "ot",
      "slug": "amos",
      "chapters_total": 9,
      "verses_total": 146,
      "chapters_drafted": 9,
      "verses_drafted": 146
    },
    {
      "book": "Obadiah",
      "code": "OBA",
      "testament": "ot",
      "slug": "obadiah",
      "chapters_total": 1,
      "verses_total": 21,
      "chapters_drafted": 1,
      "verses_drafted": 21
    },
    {
      "book": "Jonah",
      "code": "JON",
      "testament": "ot",
      "slug": "jonah",
      "chapters_total": 4,
      "verses_total": 48,
      "chapters_drafted": 4,
      "verses_drafted": 48
    },
    {
      "book": "Micah",
      "code": "MIC",
      "testament": "ot",
      "slug": "micah",
      "chapters_total": 7,
      "verses_total": 105,
      "chapters_drafted": 7,
      "verses_drafted": 105
    },
    {
      "book": "Nahum",
      "code": "NAM",
      "testament": "ot",
      "slug": "nahum",
      "chapters_total": 3,
      "verses_total": 47,
      "chapters_drafted": 3,
      "verses_drafted": 47
    },
    {
      "book": "Habakkuk",
      "code": "HAB",
      "testament": "ot",
      "slug": "habakkuk",
      "chapters_total": 3,
      "verses_total": 56,
      "chapters_drafted": 3,
      "verses_drafted": 56
    },
    {
      "book": "Zephaniah",
      "code": "ZEP",
      "testament": "ot",
      "slug": "zephaniah",
      "chapters_total": 3,
      "verses_total": 53,
      "chapters_drafted": 3,
      "verses_drafted": 53
    },
    {
      "book": "Haggai",
      "code": "HAG",
      "testament": "ot",
      "slug": "haggai",
      "chapters_total": 2,
      "verses_total": 38,
      "chapters_drafted": 2,
      "verses_drafted": 38
    },
    {
      "book": "Zechariah",
      "code": "ZEC",
      "testament": "ot",
      "slug": "zechariah",
      "chapters_total": 14,
      "verses_total": 211,
      "chapters_drafted": 14,
      "verses_drafted": 211
    },
    {
      "book": "Malachi",
      "code": "MAL",
      "testament": "ot",
      "slug": "malachi",
      "chapters_total": 4,
      "verses_total": 55,
      "chapters_drafted": 3,
      "verses_drafted": 55
    },
    {
      "book": "Tobit",
      "code": "TOB",
      "testament": "deuterocanon",
      "slug": "tobit",
      "chapters_total": 14,
      "verses_total": 244,
      "chapters_drafted": 14,
      "verses_drafted": 255
    },
    {
      "book": "Judith",
      "code": "JDT",
      "testament": "deuterocanon",
      "slug": "judith",
      "chapters_total": 16,
      "verses_total": 339,
      "chapters_drafted": 16,
      "verses_drafted": 343
    },
    {
      "book": "Additions to Esther",
      "code": "ESG",
      "testament": "deuterocanon",
      "slug": "additions_to_esther",
      "chapters_total": 6,
      "verses_total": 104,
      "chapters_drafted": 6,
      "verses_drafted": 104
    },
    {
      "book": "Wisdom of Solomon",
      "code": "WIS",
      "testament": "deuterocanon",
      "slug": "wisdom_of_solomon",
      "chapters_total": 19,
      "verses_total": 436,
      "chapters_drafted": 19,
      "verses_drafted": 442
    },
    {
      "book": "Sirach",
      "code": "SIR",
      "testament": "deuterocanon",
      "slug": "sirach",
      "chapters_total": 51,
      "verses_total": 1439,
      "chapters_drafted": 51,
      "verses_drafted": 1439
    },
    {
      "book": "Baruch",
      "code": "BAR",
      "testament": "deuterocanon",
      "slug": "baruch",
      "chapters_total": 5,
      "verses_total": 141,
      "chapters_drafted": 5,
      "verses_drafted": 141
    },
    {
      "book": "Letter of Jeremiah",
      "code": "LJE",
      "testament": "deuterocanon",
      "slug": "letter_of_jeremiah",
      "chapters_total": 1,
      "verses_total": 72,
      "chapters_drafted": 1,
      "verses_drafted": 72
    },
    {
      "book": "Prayer of Azariah and Song of the Three",
      "code": "PAZ",
      "testament": "deuterocanon",
      "slug": "prayer_of_azariah",
      "chapters_total": 1,
      "verses_total": 67,
      "chapters_drafted": 1,
      "verses_drafted": 67
    },
    {
      "book": "Susanna",
      "code": "SUS",
      "testament": "deuterocanon",
      "slug": "susanna",
      "chapters_total": 1,
      "verses_total": 64,
      "chapters_drafted": 1,
      "verses_drafted": 64
    },
    {
      "book": "Bel and the Dragon",
      "code": "BEL",
      "testament": "deuterocanon",
      "slug": "bel_and_the_dragon",
      "chapters_total": 1,
      "verses_total": 42,
      "chapters_drafted": 1,
      "verses_drafted": 42
    },
    {
      "book": "1 Maccabees",
      "code": "1MA",
      "testament": "deuterocanon",
      "slug": "1_maccabees",
      "chapters_total": 16,
      "verses_total": 924,
      "chapters_drafted": 16,
      "verses_drafted": 940
    },
    {
      "book": "2 Maccabees",
      "code": "2MA",
      "testament": "deuterocanon",
      "slug": "2_maccabees",
      "chapters_total": 15,
      "verses_total": 555,
      "chapters_drafted": 15,
      "verses_drafted": 583
    },
    {
      "book": "3 Maccabees",
      "code": "3MA",
      "testament": "deuterocanon",
      "slug": "3_maccabees",
      "chapters_total": 7,
      "verses_total": 228,
      "chapters_drafted": 7,
      "verses_drafted": 232
    },
    {
      "book": "4 Maccabees",
      "code": "4MA",
      "testament": "deuterocanon",
      "slug": "4_maccabees",
      "chapters_total": 18,
      "verses_total": 482,
      "chapters_drafted": 18,
      "verses_drafted": 503
    },
    {
      "book": "1 Esdras",
      "code": "1ES",
      "testament": "deuterocanon",
      "slug": "1_esdras",
      "chapters_total": 9,
      "verses_total": 439,
      "chapters_drafted": 9,
      "verses_drafted": 496
    },
    {
      "book": "Prayer of Manasseh",
      "code": "MAN",
      "testament": "deuterocanon",
      "slug": "prayer_of_manasseh",
      "chapters_total": 1,
      "verses_total": 15,
      "chapters_drafted": 1,
      "verses_drafted": 15
    },
    {
      "book": "Psalm 151",
      "code": "PS151",
      "testament": "deuterocanon",
      "slug": "psalm_151",
      "chapters_total": 1,
      "verses_total": 7,
      "chapters_drafted": 1,
      "verses_drafted": 7
    },
    {
      "book": "Psalms of Solomon",
      "code": "PSS",
      "testament": "deuterocanon",
      "slug": "psalms_of_solomon",
      "chapters_total": 18,
      "verses_total": 330,
      "chapters_drafted": 18,
      "verses_drafted": 330
    },
    {
      "book": "Didache",
      "code": "DID",
      "testament": "extra_canonical",
      "slug": "didache",
      "chapters_total": 16,
      "verses_total": 100,
      "chapters_drafted": 16,
      "verses_drafted": 100
    },
    {
      "book": "1 Clement",
      "code": "1CLEM",
      "testament": "extra_canonical",
      "slug": "1_clement",
      "chapters_total": 65,
      "verses_total": 395,
      "chapters_drafted": 65,
      "verses_drafted": 395
    },
    {
      "book": "Shepherd of Hermas",
      "code": "HERM",
      "testament": "extra_canonical",
      "slug": "shepherd_of_hermas",
      "chapters_total": 63,
      "verses_total": 331,
      "chapters_drafted": 63,
      "verses_drafted": 331
    },
    {
      "book": "1 Enoch",
      "code": "ENO",
      "testament": "extra_canonical",
      "slug": "1_enoch",
      "chapters_total": 108,
      "verses_total": 843,
      "chapters_drafted": 108,
      "verses_drafted": 843
    },
    {
      "book": "Jubilees",
      "code": "JUB",
      "testament": "extra_canonical",
      "slug": "jubilees",
      "chapters_total": 50,
      "verses_total": 1023,
      "chapters_drafted": 50,
      "verses_drafted": 1154
    },
    {
      "book": "2 Esdras",
      "code": "2ES",
      "testament": "extra_canonical",
      "slug": "2_esdras",
      "chapters_total": 16,
      "verses_total": 942,
      "chapters_drafted": 16,
      "verses_drafted": 942,
      "appendix": true
    },
    {
      "book": "2 Baruch",
      "code": "2BAR",
      "testament": "extra_canonical",
      "slug": "2_baruch",
      "chapters_total": 87,
      "verses_total": 363,
      "chapters_drafted": 87,
      "verses_drafted": 363
    },
    {
      "book": "Testaments of the Twelve Patriarchs",
      "code": "T12P",
      "testament": "extra_canonical",
      "slug": "testaments_twelve_patriarchs",
      "chapters_total": 142,
      "verses_total": 945,
      "chapters_drafted": 142,
      "verses_drafted": 988
    },
    {
      "book": "Gospel of Thomas",
      "code": "GOSTH",
      "testament": "extra_canonical",
      "slug": "gospel_of_thomas",
      "chapters_total": 115,
      "verses_total": 115,
      "chapters_drafted": 115,
      "verses_drafted": 115
    },
    {
      "book": "Thunder, Perfect Mind",
      "code": "THUN",
      "testament": "extra_canonical",
      "slug": "thunder_perfect_mind",
      "chapters_total": 123,
      "verses_total": 123,
      "chapters_drafted": 123,
      "verses_drafted": 123
    },
    {
      "book": "Gospel of Truth",
      "code": "GOSTR",
      "testament": "extra_canonical",
      "slug": "gospel_of_truth",
      "chapters_total": 16,
      "verses_total": 16,
      "chapters_drafted": 16,
      "verses_drafted": 16
    }
  ],
  "recent_commits": [
    {
      "sha": "3238ec9b43407d283d0014433913bb4785f28dfc",
      "short": "3238ec9b43",
      "date": "2026-05-16T15:17:04-07:00",
      "subject": "revise: /loop batch 149 — 20 doctrine_realignments (Romans/Mark multi-2 sweep)",
      "is_revision": true
    },
    {
      "sha": "f8d8b861024a2e2cfbaa4d9bbd78359b9ad6f51f",
      "short": "f8d8b86102",
      "date": "2026-05-16T15:15:44-07:00",
      "subject": "revise: /loop batch 148 — 20 doctrine_realignments (Acts/Titus/2Cor/Rom multi-2 sweep)",
      "is_revision": true
    },
    {
      "sha": "303577599f5d83afd295cb4f7cfa1f802c833ad8",
      "short": "303577599f",
      "date": "2026-05-16T15:14:16-07:00",
      "subject": "revise: /loop batch 147 — 20 doctrine_realignments (Acts multi-2 sweep)",
      "is_revision": true
    },
    {
      "sha": "c7cf835360efe445299e271ed746b74e1e919843",
      "short": "c7cf835360",
      "date": "2026-05-16T15:12:30-07:00",
      "subject": "revise: /loop batch 146 — 20 doctrine_realignments (Matthew/Acts multi-2 sweep)",
      "is_revision": true
    },
    {
      "sha": "aa11cf29517f844b045ce2d9ceba23bf976ae2a8",
      "short": "aa11cf2951",
      "date": "2026-05-16T13:52:52-07:00",
      "subject": "revise: /loop batch 145 — 20 doctrine_realignments (Matthew multi-2 sweep)",
      "is_revision": true
    },
    {
      "sha": "826792e607ca7fb7f0f09f0f7224e6a7a2e3a20a",
      "short": "826792e607",
      "date": "2026-05-16T13:37:41-07:00",
      "subject": "revise: /loop batch 144 — 20 doctrine_realignments (John/1Thess/Rev/Matt multi-2 sweep)",
      "is_revision": true
    },
    {
      "sha": "282a5b064b1e3154341cc6a18485dbe452da8b8d",
      "short": "282a5b064b",
      "date": "2026-05-16T13:23:01-07:00",
      "subject": "revise: /loop batch 143 — 20 doctrine_realignments (John multi-2 sweep)",
      "is_revision": true
    },
    {
      "sha": "ba4bd497d384854d214cdc858ca570a7aa80dc17",
      "short": "ba4bd497d3",
      "date": "2026-05-16T13:08:01-07:00",
      "subject": "revise: /loop batch 142 — 20 doctrine_realignments (Baruch/NT multi-2 sweep)",
      "is_revision": true
    },
    {
      "sha": "a210987b90d748b4ff6f2ef7f9c75aa0d9a88acd",
      "short": "a210987b90",
      "date": "2026-05-16T12:53:00-07:00",
      "subject": "revise: /loop batch 141 — 19 doctrine_realignments (3 Maccabees multi-2 sweep)",
      "is_revision": true
    },
    {
      "sha": "00489f8f05c76232b3b1d5335f72969c21076e51",
      "short": "00489f8f05",
      "date": "2026-05-16T12:38:00-07:00",
      "subject": "revise: /loop batch 140 — 20 doctrine_realignments (3 Maccabees multi-2 sweep)",
      "is_revision": true
    },
    {
      "sha": "feaf3075e64ae84b1481188564d4916c39c0c35d",
      "short": "feaf3075e6",
      "date": "2026-05-16T12:23:05-07:00",
      "subject": "revise: /loop batch 139 — 20 doctrine_realignments (4Macc/3Macc multi-2 sweep)",
      "is_revision": true
    },
    {
      "sha": "9b6da99f66cd44aa1db3caaa73c295e6e633403b",
      "short": "9b6da99f66",
      "date": "2026-05-16T12:08:17-07:00",
      "subject": "revise: /loop batch 138 — 20 doctrine_realignments (4 Maccabees multi-2 sweep)",
      "is_revision": true
    },
    {
      "sha": "fb70e8bed15a14fda9fbc78b073cdbe99b8a4eb4",
      "short": "fb70e8bed1",
      "date": "2026-05-16T11:53:15-07:00",
      "subject": "revise: /loop batch 137 — 19 doctrine_realignments (4 Maccabees multi-2 sweep)",
      "is_revision": true
    },
    {
      "sha": "346cf36639728464b6e16eb89d3b9e759b69dd74",
      "short": "346cf36639",
      "date": "2026-05-16T11:38:24-07:00",
      "subject": "revise: /loop batch 136 — 20 doctrine_realignments (4 Maccabees multi-2 sweep)",
      "is_revision": true
    },
    {
      "sha": "089282c08dee7f154079982b3bafdfbdb5048386",
      "short": "089282c08d",
      "date": "2026-05-16T11:22:36-07:00",
      "subject": "revise: /loop batch 135 — 19 doctrine_realignments (Judith/PrMan/4Macc multi-2 sweep)",
      "is_revision": true
    },
    {
      "sha": "d409e480f012bdec31c504372b6293c16fa728c7",
      "short": "d409e480f0",
      "date": "2026-05-16T10:52:49-07:00",
      "subject": "revise: /loop batch 134 — 20 doctrine_realignments (Judith multi-2 sweep)",
      "is_revision": true
    },
    {
      "sha": "15e47d939463fea23b93e2b8bb5c8ae5e5ac1a4c",
      "short": "15e47d9394",
      "date": "2026-05-16T10:37:44-07:00",
      "subject": "revise: /loop batch 133 — 20 doctrine_realignments (Wisdom/Judith multi-2 sweep)",
      "is_revision": true
    },
    {
      "sha": "8d038a40ce0e947e2a815d93fa92e1adcf6b15cd",
      "short": "8d038a40ce",
      "date": "2026-05-16T10:22:44-07:00",
      "subject": "revise: /loop batch 132 — 20 doctrine_realignments (Wisdom of Solomon multi-2 sweep)",
      "is_revision": true
    },
    {
      "sha": "8b85d5c03e2489d5df12c693677283b41237eefc",
      "short": "8b85d5c03e",
      "date": "2026-05-16T10:07:45-07:00",
      "subject": "revise: /loop batch 131 — 20 doctrine_realignments (Wisdom of Solomon multi-2 sweep)",
      "is_revision": true
    },
    {
      "sha": "5db7a60afe9a7f59e5d41cb99c757995dc7463bf",
      "short": "5db7a60afe",
      "date": "2026-05-16T09:52:47-07:00",
      "subject": "revise: /loop batch 130 — 19 doctrine_realignments (2 Macc/Wis multi-2 sweep)",
      "is_revision": true
    },
    {
      "sha": "7240a4d9444a122b5c6ca41e625f5004d1806574",
      "short": "7240a4d944",
      "date": "2026-05-16T09:37:45-07:00",
      "subject": "revise: /loop batch 129 — 20 doctrine_realignments (2 Maccabees multi-2 sweep)",
      "is_revision": true
    },
    {
      "sha": "38f06e3234796767971a378446e33cb261ab11ae",
      "short": "38f06e3234",
      "date": "2026-05-16T09:22:59-07:00",
      "subject": "revise: /loop batch 128 — 19 doctrine_realignments (2 Maccabees multi-2 sweep)",
      "is_revision": true
    },
    {
      "sha": "78579db6b8abec015d110aabdfea50feb16d2743",
      "short": "78579db6b8",
      "date": "2026-05-16T09:07:51-07:00",
      "subject": "revise: /loop batch 127 — 19 doctrine_realignments (2 Maccabees multi-2 sweep)",
      "is_revision": true
    },
    {
      "sha": "1e8c7f4620178300ef38a097542b006cb541a9ac",
      "short": "1e8c7f4620",
      "date": "2026-05-16T08:52:52-07:00",
      "subject": "revise: /loop batch 126 — 20 doctrine_realignments (Add Esth/2 Macc multi-2 sweep)",
      "is_revision": true
    },
    {
      "sha": "60db20492dec8167ef348b736ce11898cefe7353",
      "short": "60db20492d",
      "date": "2026-05-16T08:37:57-07:00",
      "subject": "revise: /loop batch 125 — 20 doctrine_realignments (1Esd/Add Esth multi-2 sweep)",
      "is_revision": true
    },
    {
      "sha": "eb04e588f9a3b802b23c1b1801e43f6f7fa77f7b",
      "short": "eb04e588f9",
      "date": "2026-05-16T08:22:50-07:00",
      "subject": "revise: /loop batch 124 — 19 doctrine_realignments (1 Esdras multi-2 sweep)",
      "is_revision": true
    },
    {
      "sha": "ca803ecec67ca89090fd5042cb5ee8f0dd62eb60",
      "short": "ca803ecec6",
      "date": "2026-05-16T08:07:42-07:00",
      "subject": "revise: /loop batch 123 — 20 doctrine_realignments (1Macc/1Esd multi-2 sweep)",
      "is_revision": true
    },
    {
      "sha": "96d02d1b4e7f3e5f22b6c1688b56ef94e26fda8e",
      "short": "96d02d1b4e",
      "date": "2026-05-16T07:52:51-07:00",
      "subject": "revise: /loop batch 122 — 19 doctrine_realignments (1 Maccabees multi-2 sweep)",
      "is_revision": true
    },
    {
      "sha": "c58e41579d03e6003d543334aa3f949576e8b061",
      "short": "c58e41579d",
      "date": "2026-05-16T07:38:03-07:00",
      "subject": "revise: /loop batch 121 — 19 doctrine_realignments (1 Maccabees multi-2 sweep; skipped 6:11 with Hebrew placeholder)",
      "is_revision": true
    },
    {
      "sha": "1b4aefb6fa5aa4309c0c7cd4db2e8af9fdb36f16",
      "short": "1b4aefb6fa",
      "date": "2026-05-16T07:22:43-07:00",
      "subject": "revise: /loop batch 120 — 20 doctrine_realignments (1 Maccabees multi-2 sweep)",
      "is_revision": true
    },
    {
      "sha": "63d684dafd256eb25485a1e8db9f148f5da8b7c3",
      "short": "63d684dafd",
      "date": "2026-05-16T07:08:11-07:00",
      "subject": "revise: /loop batch 119 — 19 doctrine_realignments (PsSol/Susanna/PrAz/LetJer/1Macc multi-2 sweep)",
      "is_revision": true
    },
    {
      "sha": "294d1897fe320c2304e685f48b6d15ce63736a43",
      "short": "294d1897fe",
      "date": "2026-05-16T06:52:52-07:00",
      "subject": "revise: /loop batch 118 — 20 doctrine_realignments (Psalms of Solomon multi-2 sweep)",
      "is_revision": true
    },
    {
      "sha": "b76a54e7eb25aa5f09880cb002ba19217695c7ba",
      "short": "b76a54e7eb",
      "date": "2026-05-16T06:37:43-07:00",
      "subject": "revise: /loop batch 117 — 20 doctrine_realignments (Tobit/PsSol multi-2 sweep)",
      "is_revision": true
    },
    {
      "sha": "25791f710af444c0bd194e681fa6339ae446847b",
      "short": "25791f710a",
      "date": "2026-05-16T06:22:26-07:00",
      "subject": "revise: /loop batch 116 — 20 doctrine_realignments (Sirach multi-2 sweep)",
      "is_revision": true
    },
    {
      "sha": "780e5c455d3dc5683b8beea60055097dbdc176b7",
      "short": "780e5c455d",
      "date": "2026-05-16T06:08:41-07:00",
      "subject": "revise: /loop batch 115 — 20 doctrine_realignments (Sirach multi-2 sweep)",
      "is_revision": true
    },
    {
      "sha": "e3db5b9076ce07d2d364f4c78b4fb9d6febbd9ef",
      "short": "e3db5b9076",
      "date": "2026-05-16T05:52:58-07:00",
      "subject": "revise: /loop batch 114 — 20 doctrine_realignments (Sirach multi-2 sweep)",
      "is_revision": true
    },
    {
      "sha": "7ac682781a13990814c76fa028c2dde6b28c7af0",
      "short": "7ac682781a",
      "date": "2026-05-16T05:39:37-07:00",
      "subject": "revise: /loop batch 113 — 20 doctrine_realignments (Sirach multi-2 sweep)",
      "is_revision": true
    },
    {
      "sha": "089d5cc2c36d2cc96dd51234254e26b0efaf1ea7",
      "short": "089d5cc2c3",
      "date": "2026-05-16T05:22:39-07:00",
      "subject": "revise: /loop batch 112 — 20 doctrine_realignments (Sirach multi-2 sweep)",
      "is_revision": true
    },
    {
      "sha": "601d3256ffd1fc92cd3ddedf20a337bba607ed5d",
      "short": "601d3256ff",
      "date": "2026-05-16T05:07:36-07:00",
      "subject": "revise: /loop batch 111 — 20 doctrine_realignments (Sirach multi-2 sweep)",
      "is_revision": true
    },
    {
      "sha": "b7bbec6bcfe988d25efa4cc59396b620dca968e7",
      "short": "b7bbec6bcf",
      "date": "2026-05-16T04:52:36-07:00",
      "subject": "revise: /loop batch 110 — 20 doctrine_realignments (Sirach multi-2 sweep)",
      "is_revision": true
    }
  ]
}
